{
   "particleType": "phonon",
   "temperatureUnit": "K",
   "temperatures": [
      300.0
   ],
   "thermalConductivity": [
      [
         [
            63.143519484991494,
            0.06299290988058658,
            0.1255257746386259
         ],
         [
            0.06299290988058132,
            62.78270704430271,
            -0.38937647295593963
         ],
         [
            0.12552577463861772,
            -0.3893764729559332,
            62.89829418205536
         ]
      ]
   ],
   "thermalConductivityUnit": "W /(m K)"
}
